qytoolspkg/__init__.py
qytoolspkg/consts.py
qytoolspkg/VAR/LocalVAR.py
qytoolspkg/VAR/__init__.py
qytoolspkg/basictools/__init__.py
qytoolspkg/basictools/_china_cities_coordinate.py
qytoolspkg/basictools/arraytools.py
qytoolspkg/basictools/basicfunc.py
qytoolspkg/basictools/dbtools.py
qytoolspkg/basictools/dftools.py
qytoolspkg/basictools/graphtools.py
qytoolspkg/basictools/mapgeotools.py
qytoolspkg/basictools/mytypes.py
qytoolspkg/basictools/normalization.py
qytoolspkg/basictools/plottools.py
qytoolspkg/basictools/strtools.py
qytoolspkg/macroeco/__init__.py
qytoolspkg/macroeco/macroeco.py
qytoolspkg/random/__init__.py
qytoolspkg/random/graph.py
qytoolspkg/stocks/KMV.py
qytoolspkg/stocks/KMV_.py
qytoolspkg/stocks/__init__.py
qytoolspkg/stocks/_process.py
qytoolspkg/stocks/_ratios.py
qytoolspkg/stocks/backtest.py
qytoolspkg/stocks/indicators.py
qytoolspkg/stocks/info.py
qytoolspkg/stocks/ratios.py
qytoolspkg/stocks/reader.py
qytoolspkg/stocks/update.py
qytoolspkg/systemic_risk/CoVaR.py
qytoolspkg/systemic_risk/DCC_GARCH.py
qytoolspkg/systemic_risk/DebtRank.py
qytoolspkg/systemic_risk/LeaveOneOut.py
qytoolspkg/systemic_risk/MES.py
qytoolspkg/systemic_risk/MaxEntropy.py
qytoolspkg/systemic_risk/MinDensity.py
qytoolspkg/systemic_risk/SIR_DR.py
qytoolspkg/systemic_risk/SRISK.py
qytoolspkg/systemic_risk/__init__.py
qytoolspkg/systemic_risk/_cvola.py
qytoolspkg/text_analyse/__init__.py
qytoolspkg/text_analyse/domain_weights.py
qytoolspkg-0.0.4.dist-info/METADATA
qytoolspkg-0.0.4.dist-info/WHEEL
qytoolspkg-0.0.4.dist-info/top_level.txt
qytoolspkg-0.0.4.dist-info/RECORD
